ALU/32bitALU.v
module ALU32(A,B,mode,X);

    input signed [31:0] A;
    input signed [31:0] B;
    input [3:0] mode;
    output[31:0] X;

    function [32:0] operation;
        input [3:0] mode; // max16 命令
        input signed [31:0] A;
        input signed [31:0] B;

        begin
            case(mode)
                4'b0000: operation = 32'h0000_0000;     // NOP
                4'b0001: operation = A + B;           // Add
                4'b0010: operation = A - B;           // Subtract
                4'b0011: operation = A & B;           // Bitwise AND
                4'b0100: operation = A | B;           // Bitwise OR
                4'b0101: operation = A ^ B;           // Bitwise XOR
                4'b0110: operation = A << B;     // logical Shift left 
                4'b0111: operation = A >> B;     // logical Shift right
                4'b1000: operation = A >>> B ;  // arithmetic Shift right
                // ...

            endcase
        end
    endfunction

    assign X = operation(mode, A, B);


        
        

    // ALU16 alu16_0 (.A(A[15:0]), .B(B[15:0]), .cin(cin), .X(X[15:0]), .cout(C[0]));
    // ALU16 alu16_1 (.A(A[31:16]), .B(B[31:16]), .cin(C[0]), .X(X[31:16]), .cout(cout));
    
endmodule

test/32bitALU_test.v
`timescale 1ns/1ns
// test for 32bit Full Adder
module main ();

    reg [31:0] a;
    reg [31:0] b;
    wire [31:0] x;
    reg [3:0] mode;

    ALU32 alu32_0 (.A(a), .B(b), .mode(mode), .X(x));

    initial begin
        $dumpvars;
        a = 32'h00000001; //+
        b = 32'h00000002;
        mode = 1;
        #100;
        a = 32'h0000000A;
        b = 32'h00000020;
        mode = 2;
        #100;
        a = 32'b0000_0000_0000_0000_0000_0000_1100_1100;
        b = 32'b0000_0000_0000_0000_0000_0000_1100_1010;
        mode = 3;
        #100;
        mode = 4;
        #100;
        mode = 5;
        #100;
        b = 32'd2;
        mode = 6;
        #100;
        mode = 7;
        #100;
        mode = 8;
        #100;
        $finish;
    end


endmodule

dump.vcd
$date
	Mon Apr 10 17:43:40 2023
$end
$version
	Icarus Verilog
$end
$timescale
	1ns
$end
$scope module main $end
$var wire 32 ! x [31:0] $end
$var reg 32 " a [31:0] $end
$var reg 32 # b [31:0] $end
$var reg 4 $ mode [3:0] $end
$scope module alu32_0 $end
$var wire 32 % A [31:0] $end
$var wire 32 & B [31:0] $end
$var wire 4 ' mode [3:0] $end
$var wire 32 ( X [31:0] $end
$scope function operation $end
$var reg 32 ) A [31:0] $end
$var reg 32 * B [31:0] $end
$var reg 4 + mode [3:0] $end
$upscope $end
$upscope $end
$upscope $end
$enddefinitions $end
#0
$dumpvars
b1 +
b10 *
b1 )
b11 (
b1 '
b10 &
b1 %
b1 $
b10 #
b1 "
b11 !
$end
#100
b11111111111111111111111111101010 !
b11111111111111111111111111101010 (
b100000 *
b1010 )
b10 +
b10 $
b10 '
b100000 #
b100000 &
b1010 "
b1010 %
#200
b11001000 !
b11001000 (
b11001010 *
b11001100 )
b11 +
b11 $
b11 '
b11001010 #
b11001010 &
b11001100 "
b11001100 %
#300
b11001110 !
b11001110 (
b100 +
b100 $
b100 '
#400
b110 !
b110 (
b101 +
b101 $
b101 '
#500
b1100110000 !
b1100110000 (
b10 *
b110 +
b110 $
b110 '
b10 #
b10 &
#600
b110011 !
b110011 (
b111 +
b111 $
b111 '
#700
b1000 +
b1000 $
b1000 '
